pdfrw/__init__.py
pdfrw/buildxobj.py
pdfrw/compress.py
pdfrw/errors.py
pdfrw/findobjs.py
pdfrw/pagemerge.py
pdfrw/pdfreader.py
pdfrw/pdfwriter.py
pdfrw/py23_diffs.py
pdfrw/tokens.py
pdfrw/toreportlab.py
pdfrw/uncompress.py
pdfrw/objects/__init__.py
pdfrw/objects/pdfarray.py
pdfrw/objects/pdfdict.py
pdfrw/objects/pdfindirect.py
pdfrw/objects/pdfname.py
pdfrw/objects/pdfobject.py
pdfrw/objects/pdfstring.py
pdfrw-0.3.dist-info/DESCRIPTION.rst
pdfrw-0.3.dist-info/METADATA
pdfrw-0.3.dist-info/RECORD
pdfrw-0.3.dist-info/WHEEL
pdfrw-0.3.dist-info/metadata.json
pdfrw-0.3.dist-info/top_level.txt
